setup.py
bin/ktagz
ktagz.egg-info/PKG-INFO
ktagz.egg-info/SOURCES.txt
ktagz.egg-info/dependency_links.txt
ktagz.egg-info/top_level.txt
ktagzpackage/__init__.py
ktagzpackage/indexer.py
ktagzpackage/ktagz.py
ktagzpackage/query.py