Metadata-Version: 1.0
Name: ktagz
Version: 0.1.7
Summary: A command line file-tagger/file-search tool for linux
Home-page: https://github.com/shinigamiryuk/TagZ
Author: Khirod Kant Naik
Author-email: khirod234@gmail.com
License: UNKNOWN
Platform: UNKNOWN
